WholeGenomeAnalysis/Tester.py
WholeGenomeAnalysis/__init__.py
WholeGenomeAnalysis/SNP/__init__.py
WholeGenomeAnalysis/SNP/model/Amplicon.py
WholeGenomeAnalysis/SNP/model/AutoTypingResult.py
WholeGenomeAnalysis/SNP/model/Output.py
WholeGenomeAnalysis/SNP/model/PacBioObject.py
WholeGenomeAnalysis/SNP/model/Sample.py
WholeGenomeAnalysis/SNP/model/SequenceObject.py
WholeGenomeAnalysis/SNP/model/Snp.py
WholeGenomeAnalysis/SNP/model/Vcf.py
WholeGenomeAnalysis/SNP/model/__init__.py
WholeGenomeAnalysis/SNP/process/CallSnip.py
WholeGenomeAnalysis/SNP/process/QualityCalculation.py
WholeGenomeAnalysis/SNP/process/__init__.py
WholeGenomeAnalysis/SNP/process/mainProcess.py
WholeGenomeAnalysis/SNP/process/mainProcess_pacbio.py
WholeGenomeAnalysis/SNP/process/pacbioFastqGenerator.py
WholeGenomeAnalysis/SNP/process/runConvert.py
WholeGenomeAnalysis/SNP/process/testProcess.py
WholeGenomeAnalysis/SNP/reader/__init__.py
WholeGenomeAnalysis/SNP/reader/reader.py
WholeGenomeAnalysis/SNP/writer/__init__.py
WholeGenomeAnalysis/SNP/writer/writer.py
snpcaller-0.2.6.dist-info/METADATA
snpcaller-0.2.6.dist-info/WHEEL
snpcaller-0.2.6.dist-info/top_level.txt
snpcaller-0.2.6.dist-info/RECORD
