Metadata-Version: 2.1
Name: snpcaller
Version: 0.2.6
Summary: Read bam file and find the snp positions
Home-page: https://github.com/Histogenetics/GenomeAnalysis
Author: seho, sungkook
Author-email: seho@histogenetics.com
License: UNKNOWN
Download-URL: https://github.com/Histogenetics/GenomeAnalysis/archive/master.zip
Keywords: snp
Platform: UNKNOWN
Classifier: Programming Language :: Python :: 3
Classifier: Programming Language :: Python :: 3.2
Classifier: Programming Language :: Python :: 3.3
Classifier: Programming Language :: Python :: 3.4
Classifier: Programming Language :: Python :: 3.5
Classifier: Programming Language :: Python :: 3.6
Classifier: Programming Language :: Python :: 3.7
Requires-Python: >=3
